fe3h_checklist/__init__.py
fe3h_checklist/calc.py
fe3h_checklist/formatting.py
fe3h_checklist/ods_interface.py
fe3h_checklist/printer.py
fe3h_checklist/setters.py
fe3h_checklist/support_encoding.py
fe3h_checklist/data/support_levels.ods
fe3h_checklist/data/support_levels_info.ods
fe3h_checklist-0.1.1.data/scripts/fe3h-checklist
fe3h_checklist-0.1.1.dist-info/LICENSE
fe3h_checklist-0.1.1.dist-info/METADATA
fe3h_checklist-0.1.1.dist-info/WHEEL
fe3h_checklist-0.1.1.dist-info/top_level.txt
fe3h_checklist-0.1.1.dist-info/RECORD
