Metadata-Version: 2.1
Name: fe3h-checklist
Version: 0.1.1
Summary: A checklist for Fire Emblem Three Houses
Home-page: https://gitlab.namibsun.net/namibsun/python/fe3h-checklist
Author: Hermann Krumrey
Author-email: hermann@krumreyh.com
License: GNU GPL3
Platform: UNKNOWN
Classifier: License :: OSI Approved :: GNU General Public License v3 (GPLv3)
Requires-Dist: typing
Requires-Dist: colorama
Requires-Dist: pyexcel-ods
